{
    "modules": [
        {
            "config": {
                "position": [
                    344,
                    278
                ]
            },
            "name": "New Model Object",
            "value": {
                "actionGroup": {
                    "_default0_index": false,
                    "_default1_list": false,
                    "_default2_show": false,
                    "_default3_new_create": false,
                    "_default4_edit_update": false,
                    "_default5_delete": false,
                    "customActions": []
                },
                "name": "SpecialistCluster",
                "objectsettings": {
                    "addDeletedField": true,
                    "addHiddenField": true,
                    "addStarttimeEndtimeFields": true,
                    "aggregateRoot": true,
                    "categorizable": false,
                    "description": "Specialist Cluster",
                    "mapToTable": "",
                    "parentClass": "",
                    "sorting": true,
                    "type": "ValueObject",
                    "uid": "502210832933"
                },
                "propertyGroup": {
                    "properties": [
                        {
                            "allowedFileTypes": "",
                            "maxItems": "1",
                            "propertyDescription": "Title",
                            "propertyIsExcludeField": true,
                            "propertyIsL10nModeExclude": false,
                            "propertyIsNullable": false,
                            "propertyIsRequired": true,
                            "propertyName": "title",
                            "propertyType": "String",
                            "uid": "1100399550839"
                        },
                        {
                            "allowedFileTypes": "",
                            "maxItems": "1",
                            "propertyDescription": "Icon",
                            "propertyIsExcludeField": true,
                            "propertyIsL10nModeExclude": false,
                            "propertyIsNullable": false,
                            "propertyIsRequired": false,
                            "propertyName": "icon",
                            "propertyType": "String",
                            "uid": "1208577387201"
                        }
                    ]
                },
                "relationGroup": {
                    "relations": []
                }
            }
        },
        {
            "config": {
                "position": [
                    599,
                    63
                ]
            },
            "name": "New Model Object",
            "value": {
                "actionGroup": {
                    "_default0_index": false,
                    "_default1_list": false,
                    "_default2_show": false,
                    "_default3_new_create": false,
                    "_default4_edit_update": false,
                    "_default5_delete": false,
                    "customActions": []
                },
                "name": "EventFormat",
                "objectsettings": {
                    "addDeletedField": true,
                    "addHiddenField": true,
                    "addStarttimeEndtimeFields": true,
                    "aggregateRoot": true,
                    "categorizable": false,
                    "description": "Event Format",
                    "mapToTable": "",
                    "parentClass": "",
                    "sorting": true,
                    "type": "ValueObject",
                    "uid": "854098797173"
                },
                "propertyGroup": {
                    "properties": [
                        {
                            "allowedFileTypes": "",
                            "maxItems": "1",
                            "propertyDescription": "Title",
                            "propertyIsExcludeField": true,
                            "propertyIsL10nModeExclude": false,
                            "propertyIsNullable": false,
                            "propertyIsRequired": true,
                            "propertyName": "title",
                            "propertyType": "String",
                            "uid": "883781277754"
                        },
                        {
                            "allowedFileTypes": "",
                            "maxItems": "1",
                            "propertyDescription": "Icon",
                            "propertyIsExcludeField": true,
                            "propertyIsL10nModeExclude": false,
                            "propertyIsNullable": false,
                            "propertyIsRequired": false,
                            "propertyName": "icon",
                            "propertyType": "String",
                            "uid": "410070381795"
                        }
                    ]
                },
                "relationGroup": {
                    "relations": []
                }
            }
        },
        {
            "config": {
                "position": [
                    615,
                    270
                ]
            },
            "name": "New Model Object",
            "value": {
                "actionGroup": {
                    "_default0_index": false,
                    "_default1_list": false,
                    "_default2_show": false,
                    "_default3_new_create": false,
                    "_default4_edit_update": false,
                    "_default5_delete": false,
                    "customActions": []
                },
                "name": "EventMode",
                "objectsettings": {
                    "addDeletedField": true,
                    "addHiddenField": true,
                    "addStarttimeEndtimeFields": true,
                    "aggregateRoot": true,
                    "categorizable": false,
                    "description": "Event Mode",
                    "mapToTable": "",
                    "parentClass": "",
                    "sorting": true,
                    "type": "ValueObject",
                    "uid": "58375364974"
                },
                "propertyGroup": {
                    "properties": [
                        {
                            "allowedFileTypes": "",
                            "maxItems": "1",
                            "propertyDescription": "Title",
                            "propertyIsExcludeField": true,
                            "propertyIsL10nModeExclude": false,
                            "propertyIsNullable": false,
                            "propertyIsRequired": true,
                            "propertyName": "title",
                            "propertyType": "String",
                            "uid": "332273418552"
                        },
                        {
                            "allowedFileTypes": "",
                            "maxItems": "1",
                            "propertyDescription": "Icon",
                            "propertyIsExcludeField": true,
                            "propertyIsL10nModeExclude": false,
                            "propertyIsNullable": false,
                            "propertyIsRequired": false,
                            "propertyName": "icon",
                            "propertyType": "String",
                            "uid": "1563923664715"
                        }
                    ]
                },
                "relationGroup": {
                    "relations": []
                }
            }
        },
        {
            "config": {
                "position": [
                    345,
                    61
                ]
            },
            "name": "New Model Object",
            "value": {
                "actionGroup": {
                    "_default0_index": false,
                    "_default1_list": false,
                    "_default2_show": false,
                    "_default3_new_create": false,
                    "_default4_edit_update": false,
                    "_default5_delete": false,
                    "customActions": []
                },
                "name": "DidacticConcept",
                "objectsettings": {
                    "addDeletedField": true,
                    "addHiddenField": true,
                    "addStarttimeEndtimeFields": true,
                    "aggregateRoot": true,
                    "categorizable": false,
                    "description": "Didactic Concept",
                    "mapToTable": "",
                    "parentClass": "",
                    "sorting": true,
                    "type": "ValueObject",
                    "uid": "1052643668168"
                },
                "propertyGroup": {
                    "properties": [
                        {
                            "allowedFileTypes": "",
                            "maxItems": "1",
                            "propertyDescription": "Title",
                            "propertyIsExcludeField": true,
                            "propertyIsL10nModeExclude": false,
                            "propertyIsNullable": false,
                            "propertyIsRequired": true,
                            "propertyName": "title",
                            "propertyType": "String",
                            "uid": "810941322509"
                        },
                        {
                            "allowedFileTypes": "",
                            "maxItems": "1",
                            "propertyDescription": "Icon",
                            "propertyIsExcludeField": true,
                            "propertyIsL10nModeExclude": false,
                            "propertyIsNullable": false,
                            "propertyIsRequired": false,
                            "propertyName": "icon",
                            "propertyType": "String",
                            "uid": "99410575310"
                        }
                    ]
                },
                "relationGroup": {
                    "relations": []
                }
            }
        },
        {
            "config": {
                "position": [
                    82,
                    59
                ]
            },
            "name": "New Model Object",
            "value": {
                "actionGroup": {
                    "_default0_index": false,
                    "_default1_list": true,
                    "_default2_show": false,
                    "_default3_new_create": false,
                    "_default4_edit_update": false,
                    "_default5_delete": false,
                    "customActions": []
                },
                "name": "Activity",
                "objectsettings": {
                    "addDeletedField": true,
                    "addHiddenField": true,
                    "addStarttimeEndtimeFields": true,
                    "aggregateRoot": true,
                    "categorizable": false,
                    "description": "Activity",
                    "mapToTable": "",
                    "parentClass": "",
                    "sorting": false,
                    "type": "Entity",
                    "uid": "1629908641393"
                },
                "propertyGroup": {
                    "properties": [
                        {
                            "allowedFileTypes": "",
                            "maxItems": "1",
                            "propertyDescription": "Title",
                            "propertyIsExcludeField": true,
                            "propertyIsL10nModeExclude": false,
                            "propertyIsNullable": false,
                            "propertyIsRequired": true,
                            "propertyName": "title",
                            "propertyType": "String",
                            "uid": "73548745816"
                        },
                        {
                            "allowedFileTypes": "",
                            "maxItems": "1",
                            "propertyDescription": "Teaser",
                            "propertyIsExcludeField": true,
                            "propertyIsL10nModeExclude": false,
                            "propertyIsNullable": false,
                            "propertyIsRequired": false,
                            "propertyName": "teaser",
                            "propertyType": "Text",
                            "uid": "1523519596632"
                        },
                        {
                            "allowedFileTypes": "",
                            "maxItems": "1",
                            "propertyDescription": "Publication Date",
                            "propertyIsExcludeField": true,
                            "propertyIsL10nModeExclude": false,
                            "propertyIsNullable": false,
                            "propertyIsRequired": false,
                            "propertyName": "publicationDate",
                            "propertyType": "NativeDate",
                            "uid": "865266671304"
                        },
                        {
                            "allowedFileTypes": "",
                            "maxItems": "1",
                            "propertyDescription": "Link",
                            "propertyIsExcludeField": true,
                            "propertyIsL10nModeExclude": false,
                            "propertyIsNullable": false,
                            "propertyIsRequired": false,
                            "propertyName": "link",
                            "propertyType": "InputLink",
                            "uid": "307926447963"
                        }
                    ]
                },
                "relationGroup": {
                    "relations": [
                        {
                            "foreignRelationClass": "",
                            "lazyLoading": false,
                            "propertyIsExcludeField": true,
                            "relationDescription": "Didactic Concepts",
                            "relationName": "didacticConcepts",
                            "relationType": "manyToMany",
                            "relationWire": "[wired]",
                            "renderType": "selectMultipleSideBySide",
                            "uid": "808434438882"
                        },
                        {
                            "foreignRelationClass": "",
                            "lazyLoading": false,
                            "propertyIsExcludeField": true,
                            "relationDescription": "Event Formats",
                            "relationName": "eventFormats",
                            "relationType": "manyToMany",
                            "relationWire": "[wired]",
                            "renderType": "selectMultipleSideBySide",
                            "uid": "863068191728"
                        },
                        {
                            "foreignRelationClass": "",
                            "lazyLoading": false,
                            "propertyIsExcludeField": true,
                            "relationDescription": "Event Mode",
                            "relationName": "eventMode",
                            "relationType": "manyToOne",
                            "relationWire": "[wired]",
                            "renderType": "selectMultipleSideBySide",
                            "uid": "1251193965671"
                        },
                        {
                            "foreignRelationClass": "",
                            "lazyLoading": false,
                            "propertyIsExcludeField": true,
                            "relationDescription": "Specialist Cluster",
                            "relationName": "specialistCluster",
                            "relationType": "manyToOne",
                            "relationWire": "[wired]",
                            "renderType": "selectMultipleSideBySide",
                            "uid": "812933064055"
                        }
                    ]
                }
            }
        }
    ],
    "properties": {
        "backendModules": [],
        "description": "HDA CommuniTeach",
        "emConf": {
            "category": "plugin",
            "custom_category": "",
            "dependsOn": "typo3 => 11.5.0-11.5.99\n",
            "disableLocalization": false,
            "disableVersioning": false,
            "generateDocumentationTemplate": false,
            "generateEditorConfig": false,
            "generateEmptyGitRepository": false,
            "sourceLanguage": "en",
            "state": "alpha",
            "targetVersion": "11.5.0-11.5.99",
            "version": "1.0.0"
        },
        "extensionKey": "hda_communiteach",
        "name": "HDA CommuniTeach",
        "originalExtensionKey": "hda_communiteach",
        "originalVendorName": "Hda",
        "persons": [
            {
                "company": "aemka",
                "email": "matthias@aemka.de",
                "name": "Matthias Krappitz",
                "role": "Developer"
            }
        ],
        "plugins": [
            {
                "actions": {
                    "controllerActionCombinations": "Activity => list",
                    "noncacheableActions": "Activity => list"
                },
                "description": "Activity List",
                "key": "activitylist",
                "name": "Activity List"
            }
        ],
        "vendorName": "Hda"
    },
    "wires": [
        {
            "src": {
                "moduleId": 4,
                "terminal": "relationWire_0",
                "uid": "808434438882"
            },
            "tgt": {
                "moduleId": 3,
                "terminal": "SOURCES",
                "uid": "1052643668168"
            }
        },
        {
            "src": {
                "moduleId": 4,
                "terminal": "relationWire_1",
                "uid": "863068191728"
            },
            "tgt": {
                "moduleId": 1,
                "terminal": "SOURCES",
                "uid": "854098797173"
            }
        },
        {
            "src": {
                "moduleId": 4,
                "terminal": "relationWire_2",
                "uid": "1251193965671"
            },
            "tgt": {
                "moduleId": 2,
                "terminal": "SOURCES",
                "uid": "58375364974"
            }
        },
        {
            "src": {
                "moduleId": 4,
                "terminal": "relationWire_3",
                "uid": "812933064055"
            },
            "tgt": {
                "moduleId": 0,
                "terminal": "SOURCES",
                "uid": "502210832933"
            }
        }
    ],
    "storagePath": "\/var\/www\/htdocs\/t11\/typo3conf\/ext\/",
    "log": {
        "last_modified": "2023-11-29 10:38",
        "extension_builder_version": "11.0.9",
        "be_user": " (69)"
    }
}